PYPGLM/__init__.py
PYPGLM/pypglm.py
PYPGLM/utils.py
PYPGLM-0.99.11.dist-info/LICENSE.txt
PYPGLM-0.99.11.dist-info/METADATA
PYPGLM-0.99.11.dist-info/WHEEL
PYPGLM-0.99.11.dist-info/top_level.txt
PYPGLM-0.99.11.dist-info/RECORD
