Metadata-Version: 2.1
Name: PYPGLM
Version: 0.99.11
Summary: This package is designed to facilitate the modeling of probabilistic, graphical, logical systems.
Author: Salma Bayoumi, De Landtsheer Sebastien
Author-email: salma.ismail.hamed@gmail.com
License-File: LICENSE.txt
Requires-Dist: networkx
Requires-Dist: numpy
Requires-Dist: pandas
Requires-Dist: emoji
Requires-Dist: pytest
Requires-Dist: pytest-cov
Requires-Dist: openpyxl
Requires-Dist: scipy
Requires-Dist: matplotlib
Requires-Dist: gaft
Requires-Dist: seaborn
Requires-Dist: joblib
Requires-Dist: scikit-learn
